LICENSE.txt
setup.py
Topsis_Manmeet_102016089/__init__.py
Topsis_Manmeet_102016089/topsis.py
Topsis_Manmeet_102016089.egg-info/PKG-INFO
Topsis_Manmeet_102016089.egg-info/SOURCES.txt
Topsis_Manmeet_102016089.egg-info/dependency_links.txt
Topsis_Manmeet_102016089.egg-info/requires.txt
Topsis_Manmeet_102016089.egg-info/top_level.txt