Metadata-Version: 2.1
Name: Topsis-Manmeet-102016089
Version: 0.1
Summary: Topsis Implementation
Author: Manmeet Singh
Author-email: msingh5_be20@thapar.edu
License: MIT
Keywords: topsis
Classifier: Development Status :: 3 - Alpha
Classifier: Intended Audience :: Developers
Classifier: License :: OSI Approved :: MIT License
Classifier: Programming Language :: Python :: 3
Classifier: Programming Language :: Python :: 3.4
Classifier: Programming Language :: Python :: 3.5
Classifier: Programming Language :: Python :: 3.6
License-File: LICENSE.txt
